pinger/__init__.py
pinger/pinger.py
site_pinger_business_automation_partners-0.0.1.dist-info/LICENSE
site_pinger_business_automation_partners-0.0.1.dist-info/METADATA
site_pinger_business_automation_partners-0.0.1.dist-info/WHEEL
site_pinger_business_automation_partners-0.0.1.dist-info/top_level.txt
site_pinger_business_automation_partners-0.0.1.dist-info/RECORD
